{
  "clientes": [
    {
      "nome": "Guilherme Santana de Andrade",
      "cpf": "409.846.108-04",
      "rg": "473800329",
      "telefone": "(11) 970113856",
      "email": "guilherme_s_andrade@hotmail.com",
      "endereco": {
        "logradouro": "Rua teste",
        "numero": "55",
        "complemento": "casa 1",
        "bairro": "bairro teste",
        "cidade": "São Paulo",
        "estado": "",
        "cep": "03370-020",
        "uf": "SP"
      },
      "id": 1
    },
    {
      "nome": "teste",
      "cpf": "111.111.111-11",
      "rg": "11111111111111111111",
      "telefone": "(11) 111111111",
      "email": "teste@gmail.com",
      "endereco": {
        "logradouro": "teste",
        "numero": "11",
        "complemento": "teste",
        "bairro": "teste",
        "cidade": "teste",
        "estado": "",
        "cep": "11111-111",
        "uf": "SP"
      },
      "id": 2
    }
  ]
}